Metadata-Version: 2.1
Name: helloWorldTestCoolegor
Version: 0.1.2
Summary: A example Python "hello world" package
Home-page: https://github.com/Kuleshovegor
Author: Egor Kuleshov
Author-email: kuleshovegor2001@gmail.com
License: UNKNOWN
Platform: UNKNOWN
Classifier: Development Status :: 1 - Planning
Classifier: Intended Audience :: Science/Research
Classifier: Programming Language :: Python :: 2
Classifier: Programming Language :: Python :: 2.7
Classifier: Programming Language :: Python :: 3
Classifier: Programming Language :: Python :: 3.4
Classifier: Programming Language :: Python :: 3.5
Classifier: Programming Language :: Python :: 3.8
